kollabor_cli_main.py
agents/__init__.py
agents/coder/__init__.py
agents/coder/agent.json
agents/coder/api-integration.md
agents/coder/cli-pretty.md
agents/coder/code-review.md
agents/coder/database-design.md
agents/coder/debugging.md
agents/coder/dependency-management.md
agents/coder/git-workflow.md
agents/coder/refactoring.md
agents/coder/security-hardening.md
agents/coder/system_prompt.md
agents/coder/tdd.md
agents/creative-writer/__init__.py
agents/creative-writer/agent.json
agents/creative-writer/character-development.md
agents/creative-writer/dialogue-craft.md
agents/creative-writer/plot-structure.md
agents/creative-writer/revision-editing.md
agents/creative-writer/system_prompt.md
agents/creative-writer/worldbuilding.md
agents/data-analyst/__init__.py
agents/data-analyst/agent.json
agents/data-analyst/data-visualization.md
agents/data-analyst/exploratory-data-analysis.md
agents/data-analyst/pandas-data-manipulation.md
agents/data-analyst/sql-query-optimization.md
agents/data-analyst/statistical-analysis.md
agents/data-analyst/system_prompt.md
agents/default/__init__.py
agents/default/agent.json
agents/default/explore-agent-system.md
agents/default/system_prompt.md
agents/kollabor/__init__.py
agents/kollabor/analyze-plugin-lifecycle.md
agents/kollabor/analyze-terminal-rendering.md
agents/kollabor/code-review.md
agents/kollabor/debug-mcp-integration.md
agents/kollabor/debug-plugin-hooks.md
agents/kollabor/debugging.md
agents/kollabor/dependency-management.md
agents/kollabor/git-workflow.md
agents/kollabor/inspect-llm-conversation.md
agents/kollabor/monitor-event-bus.md
agents/kollabor/profile-performance.md
agents/kollabor/refactoring.md
agents/kollabor/system_prompt copy.md
agents/kollabor/system_prompt.md
agents/kollabor/trace-command-execution.md
agents/kollabor/validate-config.md
agents/research/__init__.py
agents/research/agent.json
agents/research/architecture-mapping.md
agents/research/codebase-analysis.md
agents/research/dependency-audit.md
kollabor-0.4.14.dist-info/licenses/LICENSE
kollabor-0.4.14.dist-info/METADATA
kollabor-0.4.14.dist-info/WHEEL
kollabor-0.4.14.dist-info/entry_points.txt
kollabor-0.4.14.dist-info/top_level.txt
kollabor-0.4.14.dist-info/RECORD
