Metadata-Version: 2.4
Name: kollabor
Version: 0.4.14
Summary: An advanced, highly customizable terminal-based chat application for interacting with LLMs
Author-email: Kollabor Contributors <contributors@example.com>
License: MIT
Project-URL: Homepage, https://github.com/kollaborai/kollabor-cli
Project-URL: Repository, https://github.com/kollaborai/kollabor-cli
Project-URL: Documentation, https://github.com/kollaborai/kollabor-cli/blob/main/docs/
Project-URL: Bug Tracker, https://github.com/kollaborai/kollabor-cli/issues
Project-URL: Homebrew Tap, https://github.com/kollaborai/homebrew-tap
Keywords: llm,cli,chat,terminal,ai,chatbot,assistant,kollabor,plugin-system,event-driven
Classifier: Development Status :: 4 - Beta
Classifier: Intended Audience :: Developers
Classifier: License :: OSI Approved :: MIT License
Classifier: Programming Language :: Python :: 3
Classifier: Programming Language :: Python :: 3.12
Classifier: Topic :: Communications :: Chat
Classifier: Topic :: Software Development :: Libraries :: Application Frameworks
Classifier: Topic :: Terminals
Classifier: Environment :: Console
Classifier: Operating System :: MacOS
Classifier: Operating System :: Microsoft :: Windows
Classifier: Operating System :: POSIX :: Linux
Classifier: Operating System :: Unix
Requires-Python: >=3.12
License-File: LICENSE
Requires-Dist: aiohttp>=3.10.11
Requires-Dist: psutil>=5.9.0
Requires-Dist: packaging>=23.0
Provides-Extra: dev
Requires-Dist: black>=23.0.0; extra == "dev"
Requires-Dist: mypy>=1.0.0; extra == "dev"
Requires-Dist: flake8>=6.0.0; extra == "dev"
Requires-Dist: pytest>=7.0.0; extra == "dev"
Requires-Dist: pytest-asyncio>=0.21.0; extra == "dev"
Dynamic: license-file
